huisbaasje/__init__.py
huisbaasje/const.py
huisbaasje/exceptions.py
huisbaasje/huisbaasje.py
huisbaasje_client-0.1.0.dist-info/LICENSE
huisbaasje_client-0.1.0.dist-info/METADATA
huisbaasje_client-0.1.0.dist-info/WHEEL
huisbaasje_client-0.1.0.dist-info/top_level.txt
huisbaasje_client-0.1.0.dist-info/RECORD
