Metadata-Version: 2.1
Name: huisbaasje-client
Version: 0.1.0
Summary: Client for Huisbaasje
Home-page: https://github.com/denniss17/huisbaasje-client
Author: Dennis Schroer
Author-email: dev@dennisschroer.nl
License: UNKNOWN
Platform: UNKNOWN
Classifier: Intended Audience :: Developers
Classifier: License :: OSI Approved :: Apache Software License
Classifier: Operating System :: OS Independent
Classifier: Programming Language :: Python :: 3
Classifier: Topic :: Home Automation
Requires-Python: >=3.6
